simplegoogle_scraper_python/__init__.py
simplegoogle_scraper_python/custom_exceptions.py
simplegoogle_scraper_python/logger.py
simplegoogle_scraper_python/scrapeGooGle_results.py
simplegoogle_scraper_python-0.1.8.dist-info/LICENSE
simplegoogle_scraper_python-0.1.8.dist-info/METADATA
simplegoogle_scraper_python-0.1.8.dist-info/WHEEL
simplegoogle_scraper_python-0.1.8.dist-info/top_level.txt
simplegoogle_scraper_python-0.1.8.dist-info/RECORD
